{
  "last_updated": "2026-02-09T08:40:08.957752",
  "predictions": [
    {
      "game_id": 267110,
      "away_team": "Detroit Pistons",
      "home_team": "Charlotte Hornets",
      "away_team_id": 170,
      "home_team_id": 158,
      "start_time": "2026-02-10T00:00:00.000Z",
      "predicted_total": 232.39,
      "market_line": 223.5,
      "difference": 8.89,
      "difference_pct": 3.98,
      "recommendation": "over",
      "odds": "-105",
      "book_id": "15",
      "book_name": "DraftKings"
    },
    {
      "game_id": 267111,
      "away_team": "Utah Jazz",
      "home_team": "Miami Heat",
      "away_team_id": 173,
      "home_team_id": 160,
      "start_time": "2026-02-10T00:30:00.000Z",
      "predicted_total": 235.71,
      "market_line": 240.5,
      "difference": -4.79,
      "difference_pct": -1.99,
      "recommendation": "under",
      "odds": "-105",
      "book_id": "15",
      "book_name": "DraftKings"
    },
    {
      "game_id": 267112,
      "away_team": "Milwaukee Bucks",
      "home_team": "Orlando Magic",
      "away_team_id": 172,
      "home_team_id": 161,
      "start_time": "2026-02-10T00:30:00.000Z",
      "predicted_total": 230.35,
      "market_line": 218.5,
      "difference": 11.85,
      "difference_pct": 5.42,
      "recommendation": "over",
      "odds": "-106",
      "book_id": "15",
      "book_name": "DraftKings"
    },
    {
      "game_id": 267113,
      "away_team": "Chicago Bulls",
      "home_team": "Brooklyn Nets",
      "away_team_id": 169,
      "home_team_id": 165,
      "start_time": "2026-02-10T00:30:00.000Z",
      "predicted_total": 230.8,
      "market_line": 223,
      "difference": 7.8,
      "difference_pct": 3.5,
      "recommendation": "over",
      "odds": "-105",
      "book_id": "15",
      "book_name": "DraftKings"
    },
    {
      "game_id": 267114,
      "away_team": "Atlanta Hawks",
      "home_team": "Minnesota Timberwolves",
      "away_team_id": 159,
      "home_team_id": 171,
      "start_time": "2026-02-10T01:00:00.000Z",
      "predicted_total": 233.28,
      "market_line": 238.5,
      "difference": -5.22,
      "difference_pct": -2.19,
      "recommendation": "under",
      "odds": "-108",
      "book_id": "15",
      "book_name": "DraftKings"
    },
    {
      "game_id": 267115,
      "away_team": "Sacramento Kings",
      "home_team": "New Orleans Pelicans",
      "away_team_id": 185,
      "home_team_id": 179,
      "start_time": "2026-02-10T01:00:00.000Z",
      "predicted_total": 234.35,
      "market_line": 231.5,
      "difference": 2.85,
      "difference_pct": 1.23,
      "recommendation": "over",
      "odds": "-105",
      "book_id": "15",
      "book_name": "DraftKings"
    },
    {
      "game_id": 267116,
      "away_team": "Cleveland Cavaliers",
      "home_team": "Denver Nuggets",
      "away_team_id": 167,
      "home_team_id": 174,
      "start_time": "2026-02-10T02:00:00.000Z",
      "predicted_total": 239.1,
      "market_line": 237.5,
      "difference": 1.6,
      "difference_pct": 0.67,
      "recommendation": null,
      "odds": null,
      "book_id": "15",
      "book_name": "DraftKings"
    },
    {
      "game_id": 267117,
      "away_team": "Oklahoma City Thunder",
      "home_team": "Los Angeles Lakers",
      "away_team_id": 175,
      "home_team_id": 186,
      "start_time": "2026-02-10T03:00:00.000Z",
      "predicted_total": 231.2,
      "market_line": 223.5,
      "difference": 7.7,
      "difference_pct": 3.45,
      "recommendation": "over",
      "odds": "-105",
      "book_id": "15",
      "book_name": "DraftKings"
    },
    {
      "game_id": 267118,
      "away_team": "Philadelphia 76ers",
      "home_team": "Portland Trail Blazers",
      "away_team_id": 163,
      "home_team_id": 176,
      "start_time": "2026-02-10T03:00:00.000Z",
      "predicted_total": 232.59,
      "market_line": 230.5,
      "difference": 2.09,
      "difference_pct": 0.91,
      "recommendation": "over",
      "odds": "-110",
      "book_id": "15",
      "book_name": "DraftKings"
    },
    {
      "game_id": 267119,
      "away_team": "Memphis Grizzlies",
      "home_team": "Golden State Warriors",
      "away_team_id": 177,
      "home_team_id": 182,
      "start_time": "2026-02-10T03:00:00.000Z",
      "predicted_total": 231.72,
      "market_line": 223.5,
      "difference": 8.22,
      "difference_pct": 3.68,
      "recommendation": "over",
      "odds": "-106",
      "book_id": "15",
      "book_name": "DraftKings"
    }
  ]
}